CHANGES.txt
COPYRIGHT.txt
LICENSE.txt
README.txt
bootstrap.py
buildout.cfg
setup.py
src/zope/__init__.py
src/zope.app.zapi.egg-info/PKG-INFO
src/zope.app.zapi.egg-info/SOURCES.txt
src/zope.app.zapi.egg-info/dependency_links.txt
src/zope.app.zapi.egg-info/namespace_packages.txt
src/zope.app.zapi.egg-info/not-zip-safe
src/zope.app.zapi.egg-info/requires.txt
src/zope.app.zapi.egg-info/top_level.txt
src/zope/app/__init__.py
src/zope/app/zapi/README.txt
src/zope/app/zapi/__init__.py
src/zope/app/zapi/configure.zcml
src/zope/app/zapi/interfaces.py
src/zope/app/zapi/tests.py